texturize/__init__.py
texturize/__main__.py
texturize/api.py
texturize/app.py
texturize/commands.py
texturize/critics.py
texturize/io.py
texturize/logger.py
texturize/match.py
texturize/patch.py
texturize/solvers.py
texturize-0.14.1.dist-info/LICENSE
texturize-0.14.1.dist-info/METADATA
texturize-0.14.1.dist-info/WHEEL
texturize-0.14.1.dist-info/entry_points.txt
texturize-0.14.1.dist-info/RECORD
