Metadata-Version: 2.1
Name: texturize
Version: 0.14.1
Summary: 🤖🖌️ Generate new photo-realistic textures similar to a source image.
Home-page: https://github.com/photogeniq/texturize
License: AGPL-3.0
Author: Alex J. Champandard
Author-email: 445208+alexjc@users.noreply.github.com
Requires-Python: >=3.7,<4.0
Classifier: Development Status :: 3 - Alpha
Classifier: License :: OSI Approved :: GNU Affero General Public License v3
Classifier: Programming Language :: Python :: 3
Classifier: Programming Language :: Python :: 3.7
Classifier: Programming Language :: Python :: 3.8
Classifier: Programming Language :: Python :: 3.9
Classifier: Programming Language :: Python :: 3.10
Classifier: Programming Language :: Python :: 3.11
Classifier: Topic :: Multimedia :: Graphics
Requires-Dist: creativeai (>=0.2.1,<0.3.0)
Requires-Dist: docopt (>=0.6.2,<0.7.0)
Requires-Dist: progressbar2 (>=4.2.0,<5.0.0)
Requires-Dist: schema (>=0.7.5,<0.8.0)
Project-URL: Repository, https://github.com/photogeniq/texturize
